{
    "string":[
        {
            "name":"DHTypeName_Camera",
            "value":"པར་ཆས་"
        },
        {
            "name":"pause",
            "value":"སྐབས་སྡོད།"
        },
        {
            "name":"disconnect",
            "value":"སྦྲེལ་ལམ་གཅོད་པ།"
        },
        {
            "name":"connected_to",
            "value":"%1$sལ་སྦྲེལ་མཐུད་བྱུང་ཟིན།"
        },
        {
            "name":"stop_device",
            "value":"སྒྲིག་ཆས་འདིའི་%1$sབཀོལ་མཚམས་འཇོག་པའི་ཆེད་དུ་སྦྲེལ་མཐུད་གཅད་ཆོག"
        },
        {
            "name":"DHTypeName_Mic",
            "value":"སྐད་སྦུག་"
        },
        {
            "name":"continue",
            "value":"མུ་མཐུད།"
        },
        {
            "name":"continue_desc_text",
            "value":"སྒྲིག་ཆས་གཅིག་གི་ཐོག་ཏུ་ནང་དོན་བཤར་ལྟ་དང་རྩོམ་སྒྲིག་བྱས་རྗེས། དེ་ནས་ཉེ་འགྲམ་གྱི་ཧྭ་ཝེ་ཐོ་ཨང་གཅིག་པ་ཐོ་འཇུག་བྱས་ཡོད་པའི་སྒྲིག་ཆས་གཞན་ཞིག་གི་ཅོག་ངོས་ཀྱི་ལས་འགན་ཚན་བྱང་ཐོག་ཏུ་འཕྲོ་མཐུད་རིས་རྟགས་ལ་བརྡབས་ཚེ། མུ་མཐུད་བཀོལ་ཐུབ། %s"
        },
        {
            "name":"continue_title",
            "value":"འཕྲོ་མཐུད།"
        },
        {
            "name":"continue_privacy_text",
            "value":"ཞབས་ཞུ་འདིས་ WLAN དང་སོ་སྔོན་རྩོལ་ནུས་བཀོལ་དགོས་ཤིང་། སྒྲིག་ཆས་ཀྱི་མིང་ཀློག་ལེན་བྱས་ནས་འཕྲོ་མཐུད་བྱ་ཡུལ་གྱི་སྒྲིག་ཆས་ལ་བརྒྱུད་སྐྱེལ་བྱ། བསད་སྤར་ཁ་ཕྱེ་ཚེ། ཁྱེད་ཀྱིས་གོང་གི་ནང་དོན་ལ་མོས་མཐུན་བྱེད་པ་མཚོན།"
        },
        {
            "name":"learn_more",
            "value":"ཞིབ་ཕྲའི་གནས་ཚུལ་ལ་རྒྱུས་ལོན།"
        },
        {
            "name":"update_version_prompt",
            "value":"ཕ་རོལ་པོས་ HarmonyOS NEXT དང་དེ་ཡན་གྱི་པར་གཞིར་རིམ་པ་སྤོར་དགོས།"
        }
    ]
}